LICENSE
MANIFEST.in
README.md
setup.py
chatette_qiu/__init__.py
chatette_qiu/__main__.py
chatette_qiu/deprecations.py
chatette_qiu/facade.py
chatette_qiu/generator.py
chatette_qiu/utils.py
chatette_qiu.egg-info/PKG-INFO
chatette_qiu.egg-info/SOURCES.txt
chatette_qiu.egg-info/dependency_links.txt
chatette_qiu.egg-info/requires.txt
chatette_qiu.egg-info/top_level.txt
chatette_qiu/adapters/__init__.py
chatette_qiu/adapters/_base.py
chatette_qiu/adapters/factory.py
chatette_qiu/adapters/jsonl.py
chatette_qiu/adapters/rasa.py
chatette_qiu/cli/__init__.py
chatette_qiu/cli/interpreter.py
chatette_qiu/cli/terminal_writer.py
chatette_qiu/cli/interactive_commands/__init__.py
chatette_qiu/cli/interactive_commands/add_rule_command.py
chatette_qiu/cli/interactive_commands/command_strategy.py
chatette_qiu/cli/interactive_commands/declare_command.py
chatette_qiu/cli/interactive_commands/delete_command.py
chatette_qiu/cli/interactive_commands/examples_command.py
chatette_qiu/cli/interactive_commands/execute_command.py
chatette_qiu/cli/interactive_commands/exist_command.py
chatette_qiu/cli/interactive_commands/exit_command.py
chatette_qiu/cli/interactive_commands/generate_command.py
chatette_qiu/cli/interactive_commands/hide_command.py
chatette_qiu/cli/interactive_commands/parse_command.py
chatette_qiu/cli/interactive_commands/rename_command.py
chatette_qiu/cli/interactive_commands/rule_command.py
chatette_qiu/cli/interactive_commands/save_command.py
chatette_qiu/cli/interactive_commands/set_modifier_command.py
chatette_qiu/cli/interactive_commands/show_command.py
chatette_qiu/cli/interactive_commands/stats_command.py
chatette_qiu/cli/interactive_commands/unhide_command.py
chatette_qiu/modifiers/__init__.py
chatette_qiu/modifiers/representation.py
chatette_qiu/parsing/__init__.py
chatette_qiu/parsing/line_count_file_wrapper.py
chatette_qiu/parsing/parser.py
chatette_qiu/parsing/parser_utils.py
chatette_qiu/parsing/tokenizer.py
chatette_qiu/units/__init__.py
chatette_qiu/units/alias/__init__.py
chatette_qiu/units/alias/definition.py
chatette_qiu/units/alias/rule_content.py
chatette_qiu/units/choice/__init__.py
chatette_qiu/units/choice/rule_content.py
