Metadata-Version: 2.1
Name: chatette-qiu
Version: 1.4.3
Summary: A dataset generator for Rasa NLU,copy from https://github.com/SimGus/Chatette,
Home-page: https://github.com/fanfanfeng/Chatette
Author: SimGus
License: MIT
Platform: UNKNOWN
Classifier: Programming Language :: Python :: 3
Classifier: License :: OSI Approved :: MIT License
Classifier: Operating System :: OS Independent
Classifier: Environment :: Console
Classifier: Intended Audience :: Developers
Classifier: Topic :: Utilities
Classifier: Topic :: Text Processing
Classifier: Topic :: Communications
